modal_mcp_toolbox/__init__.py
modal_mcp_toolbox/__main__.py
modal_mcp_toolbox/code.py
modal_mcp_toolbox/flux.py
iflow_mcp_modal_mcp_toolbox-0.1.12.dist-info/METADATA
iflow_mcp_modal_mcp_toolbox-0.1.12.dist-info/WHEEL
iflow_mcp_modal_mcp_toolbox-0.1.12.dist-info/entry_points.txt
iflow_mcp_modal_mcp_toolbox-0.1.12.dist-info/licenses/LICENSE
iflow_mcp_modal_mcp_toolbox-0.1.12.dist-info/RECORD
